sto/__init__.py
sto/db.py
sto/distribution.py
sto/friendlytime.py
sto/identityprovider.py
sto/time.py
sto/cli/__init__.py
sto/cli/main.py
sto/ethereum/__init__.py
sto/ethereum/account.py
sto/ethereum/broadcast.py
sto/ethereum/diagnostics.py
sto/ethereum/distribution.py
sto/ethereum/exceptions.py
sto/ethereum/issuance.py
sto/ethereum/last.py
sto/ethereum/linking.py
sto/ethereum/nonce.py
sto/ethereum/scanner.py
sto/ethereum/status.py
sto/ethereum/tokenscan.py
sto/ethereum/txservice.py
sto/ethereum/utils.py
sto/generic/__init__.py
sto/generic/captable.py
sto/generic/reference.py
sto/models/__init__.py
sto/models/broadcastaccount.py
sto/models/implementation.py
sto/models/tokenscan.py
sto/models/utils.py
sto-0.4.1.dist-info/LICENSE.txt
sto-0.4.1.dist-info/METADATA
sto-0.4.1.dist-info/WHEEL
sto-0.4.1.dist-info/entry_points.txt
sto-0.4.1.dist-info/top_level.txt
sto-0.4.1.dist-info/RECORD
