Metadata-Version: 2.1
Name: sto
Version: 0.4.1
Summary: Security token manager
Home-page: https://docs.tokenmarket.net
Author: TokenMarket Ltd.
Author-email: mikko@tokenmarket.net
License: Apache 2.0
Keywords: ethereum blockchain smartcontract security token
Platform: UNKNOWN
Classifier: Development Status :: 3 - Alpha
Classifier: Intended Audience :: Developers
Classifier: Natural Language :: English
Classifier: Programming Language :: Python :: 3
Classifier: Programming Language :: Python :: 3.6
Requires-Dist: eth-typing (<2)
Requires-Dist: eth-abi (<1.3)
Requires-Dist: web3[tester]
Requires-Dist: coloredlogs
Requires-Dist: colorama
Requires-Dist: tabulate
Requires-Dist: sqlalchemy (>=1.3.0b1)
Requires-Dist: tqdm
Requires-Dist: configobj
Requires-Dist: click
Requires-Dist: arrow
Requires-Dist: pysha3 (<2.0.0)
Provides-Extra: dev
Requires-Dist: bumpversion (<1,>=0.5.3) ; extra == 'dev'
Requires-Dist: wheel ; extra == 'dev'
Requires-Dist: sphinx ; extra == 'dev'
Requires-Dist: sphinx-rtd-theme (==0.4.2) ; extra == 'dev'
Requires-Dist: setuptools ; extra == 'dev'
Provides-Extra: test
Requires-Dist: pytest ; extra == 'test'
